<annotation>
	 <folder>VOC_format</folder> 
	 <filename>DSC00116</filename> 
	 <source> 
	 	 <database>Royal Garden Edinburgh</database>
	 </source> 
	 <size> 
	 	 <width>5472</width> 
	 	 <height>3648</height> 
	 	 <depth>3</depth> 
	 </size> 
	 <segmented>0</segmented> 
	 <object> 
	 	 <name>branch_1</name> 
	 	 <pose>Unspecified</pose> 
	 	 <truncated>0</truncated> 
	 	 <difficult>0</difficult> 
	 	 <bndbox> 
	 	 	 <xmin>4487</xmin> 
	 	 	 <ymin> 2953</ymin> 
	 	 	 <xmax>4833</xmax> 
	 	 	 <ymax>3648</ymax> 
	 	 </bndbox> 
	 <object> 
	 	 <vectors> 
	 	 	 <direction_vector> 
	 	 	 	 <x_start>4664</x_start> 
	 	 	 	 <y_start>3285</y_start> 
	 	 	 	 <x_end>4706</x_end> 
	 	 	 	 <y_end>3138</y_end> 
	 	 	 </direction_vector> 
	 	 	 <radius_vector> 
	 	 	 	 <x_start>4664</x_start> 
	 	 	 	 <y_start>3285</y_start> 
	 	 	 	 <x_end>4598</x_end> 
	 	 	 	 <y_end>3268</y_end> 
	 	 	 </radius_vectors> 
	 	 </vectors> 
	 <object> 
	 	 <name>branch_2</name> 
	 	 <pose>Unspecified</pose> 
	 	 <truncated>0</truncated> 
	 	 <difficult>0</difficult> 
	 	 <bndbox> 
	 	 	 <xmin>4658</xmin> 
	 	 	 <ymin> 2613</ymin> 
	 	 	 <xmax>4849</xmax> 
	 	 	 <ymax>2945</ymax> 
	 	 </bndbox> 
	 <object> 
	 	 <vectors> 
	 	 	 <direction_vector> 
	 	 	 	 <x_start>4755</x_start> 
	 	 	 	 <y_start>2790</y_start> 
	 	 	 	 <x_end>4764</x_end> 
	 	 	 	 <y_end>2682</y_end> 
	 	 	 </direction_vector> 
	 	 	 <radius_vector> 
	 	 	 	 <x_start>4755</x_start> 
	 	 	 	 <y_start>2790</y_start> 
	 	 	 	 <x_end>4683</x_end> 
	 	 	 	 <y_end>2784</y_end> 
	 	 	 </radius_vectors> 
	 	 </vectors> 
	 <object> 
	 	 <name>branch_3</name> 
	 	 <pose>Unspecified</pose> 
	 	 <truncated>0</truncated> 
	 	 <difficult>0</difficult> 
	 	 <bndbox> 
	 	 	 <xmin>5246</xmin> 
	 	 	 <ymin> 3250</ymin> 
	 	 	 <xmax>5466</xmax> 
	 	 	 <ymax>3368</ymax> 
	 	 </bndbox> 
	 <object> 
	 	 <vectors> 
	 	 	 <direction_vector> 
	 	 	 	 <x_start>5353</x_start> 
	 	 	 	 <y_start>3310</y_start> 
	 	 	 	 <x_end>5272</x_end> 
	 	 	 	 <y_end>3294</y_end> 
	 	 	 </direction_vector> 
	 	 	 <radius_vector> 
	 	 	 	 <x_start>5353</x_start> 
	 	 	 	 <y_start>3310</y_start> 
	 	 	 	 <x_end>5341</x_end> 
	 	 	 	 <y_end>3342</y_end> 
	 	 	 </radius_vectors> 
	 	 </vectors> 
	 <object> 
	 	 <name>branch_4</name> 
	 	 <pose>Unspecified</pose> 
	 	 <truncated>0</truncated> 
	 	 <difficult>0</difficult> 
	 	 <bndbox> 
	 	 	 <xmin>5096</xmin> 
	 	 	 <ymin> 3189</ymin> 
	 	 	 <xmax>5269</xmax> 
	 	 	 <ymax>3333</ymax> 
	 	 </bndbox> 
	 <object> 
	 	 <vectors> 
	 	 	 <direction_vector> 
	 	 	 	 <x_start>5184</x_start> 
	 	 	 	 <y_start>3261</y_start> 
	 	 	 	 <x_end>5137</x_end> 
	 	 	 	 <y_end>3231</y_end> 
	 	 	 </direction_vector> 
	 	 	 <radius_vector> 
	 	 	 	 <x_start>5184</x_start> 
	 	 	 	 <y_start>3261</y_start> 
	 	 	 	 <x_end>5168</x_end> 
	 	 	 	 <y_end>3287</y_end> 
	 	 	 </radius_vectors> 
	 	 </vectors> 
	 <object> 
	 	 <name>branch_5</name> 
	 	 <pose>Unspecified</pose> 
	 	 <truncated>0</truncated> 
	 	 <difficult>0</difficult> 
	 	 <bndbox> 
	 	 	 <xmin>4846</xmin> 
	 	 	 <ymin> 2949</ymin> 
	 	 	 <xmax>5144</xmax> 
	 	 	 <ymax>3210</ymax> 
	 	 </bndbox> 
	 <object> 
	 	 <vectors> 
	 	 	 <direction_vector> 
	 	 	 	 <x_start>5017</x_start> 
	 	 	 	 <y_start>3129</y_start> 
	 	 	 	 <x_end>4964</x_end> 
	 	 	 	 <y_end>3073</y_end> 
	 	 	 </direction_vector> 
	 	 	 <radius_vector> 
	 	 	 	 <x_start>5017</x_start> 
	 	 	 	 <y_start>3129</y_start> 
	 	 	 	 <x_end>4997</x_end> 
	 	 	 	 <y_end>3148</y_end> 
	 	 	 </radius_vectors> 
	 	 </vectors> 
	 <object> 
	 	 <name>branch_6</name> 
	 	 <pose>Unspecified</pose> 
	 	 <truncated>0</truncated> 
	 	 <difficult>0</difficult> 
	 	 <bndbox> 
	 	 	 <xmin>4498</xmin> 
	 	 	 <ymin> 2287</ymin> 
	 	 	 <xmax>4869</xmax> 
	 	 	 <ymax>2947</ymax> 
	 	 </bndbox> 
	 <object> 
	 	 <vectors> 
	 	 	 <direction_vector> 
	 	 	 	 <x_start>4674</x_start> 
	 	 	 	 <y_start>2638</y_start> 
	 	 	 	 <x_end>4621</x_end> 
	 	 	 	 <y_end>2532</y_end> 
	 	 	 </direction_vector> 
	 	 	 <radius_vector> 
	 	 	 	 <x_start>4674</x_start> 
	 	 	 	 <y_start>2638</y_start> 
	 	 	 	 <x_end>4644</x_end> 
	 	 	 	 <y_end>2652</y_end> 
	 	 	 </radius_vectors> 
	 	 </vectors> 
	 <object> 
	 	 <name>branch_7</name> 
	 	 <pose>Unspecified</pose> 
	 	 <truncated>0</truncated> 
	 	 <difficult>0</difficult> 
	 	 <bndbox> 
	 	 	 <xmin>2749</xmin> 
	 	 	 <ymin> 907</ymin> 
	 	 	 <xmax>2961</xmax> 
	 	 	 <ymax>1617</ymax> 
	 	 </bndbox> 
	 <object> 
	 	 <vectors> 
	 	 	 <direction_vector> 
	 	 	 	 <x_start>2841</x_start> 
	 	 	 	 <y_start>1284</y_start> 
	 	 	 	 <x_end>2841</x_end> 
	 	 	 	 <y_end>1130</y_end> 
	 	 	 </direction_vector> 
	 	 	 <radius_vector> 
	 	 	 	 <x_start>2841</x_start> 
	 	 	 	 <y_start>1284</y_start> 
	 	 	 	 <x_end>2775</x_end> 
	 	 	 	 <y_end>1284</y_end> 
	 	 	 </radius_vectors> 
	 	 </vectors> 
	 <object> 
	 	 <name>branch_8</name> 
	 	 <pose>Unspecified</pose> 
	 	 <truncated>0</truncated> 
	 	 <difficult>0</difficult> 
	 	 <bndbox> 
	 	 	 <xmin>2759</xmin> 
	 	 	 <ymin> 1589</ymin> 
	 	 	 <xmax>2939</xmax> 
	 	 	 <ymax>2194</ymax> 
	 	 </bndbox> 
	 <object> 
	 	 <vectors> 
	 	 	 <direction_vector> 
	 	 	 	 <x_start>2857</x_start> 
	 	 	 	 <y_start>1899</y_start> 
	 	 	 	 <x_end>2867</x_end> 
	 	 	 	 <y_end>1742</y_end> 
	 	 	 </direction_vector> 
	 	 	 <radius_vector> 
	 	 	 	 <x_start>2857</x_start> 
	 	 	 	 <y_start>1899</y_start> 
	 	 	 	 <x_end>2784</x_end> 
	 	 	 	 <y_end>1904</y_end> 
	 	 	 </radius_vectors> 
	 	 </vectors> 
	 <object> 
	 	 <name>branch_9</name> 
	 	 <pose>Unspecified</pose> 
	 	 <truncated>0</truncated> 
	 	 <difficult>0</difficult> 
	 	 <bndbox> 
	 	 	 <xmin>2749</xmin> 
	 	 	 <ymin> 2172</ymin> 
	 	 	 <xmax>2904</xmax> 
	 	 	 <ymax>2767</ymax> 
	 	 </bndbox> 
	 <object> 
	 	 <vectors> 
	 	 	 <direction_vector> 
	 	 	 	 <x_start>2825</x_start> 
	 	 	 	 <y_start>2460</y_start> 
	 	 	 	 <x_end>2825</x_end> 
	 	 	 	 <y_end>2335</y_end> 
	 	 	 </direction_vector> 
	 	 	 <radius_vector> 
	 	 	 	 <x_start>2825</x_start> 
	 	 	 	 <y_start>2460</y_start> 
	 	 	 	 <x_end>2764</x_end> 
	 	 	 	 <y_end>2457</y_end> 
	 	 	 </radius_vectors> 
	 	 </vectors> 
	 <object> 
	 	 <name>branch_10</name> 
	 	 <pose>Unspecified</pose> 
	 	 <truncated>0</truncated> 
	 	 <difficult>0</difficult> 
	 	 <bndbox> 
	 	 	 <xmin>2719</xmin> 
	 	 	 <ymin> 2740</ymin> 
	 	 	 <xmax>2897</xmax> 
	 	 	 <ymax>2950</ymax> 
	 	 </bndbox> 
	 <object> 
	 	 <vectors> 
	 	 	 <direction_vector> 
	 	 	 	 <x_start>2795</x_start> 
	 	 	 	 <y_start>2878</y_start> 
	 	 	 	 <x_end>2807</x_end> 
	 	 	 	 <y_end>2820</y_end> 
	 	 	 </direction_vector> 
	 	 	 <radius_vector> 
	 	 	 	 <x_start>2795</x_start> 
	 	 	 	 <y_start>2878</y_start> 
	 	 	 	 <x_end>2744</x_end> 
	 	 	 	 <y_end>2865</y_end> 
	 	 	 </radius_vectors> 
	 	 </vectors> 
	 <object> 
	 	 <name>branch_11</name> 
	 	 <pose>Unspecified</pose> 
	 	 <truncated>0</truncated> 
	 	 <difficult>0</difficult> 
	 	 <bndbox> 
	 	 	 <xmin>2674</xmin> 
	 	 	 <ymin> 2950</ymin> 
	 	 	 <xmax>2869</xmax> 
	 	 	 <ymax>3163</ymax> 
	 	 </bndbox> 
	 <object> 
	 	 <vectors> 
	 	 	 <direction_vector> 
	 	 	 	 <x_start>2742</x_start> 
	 	 	 	 <y_start>3053</y_start> 
	 	 	 	 <x_end>2777</x_end> 
	 	 	 	 <y_end>3008</y_end> 
	 	 	 </direction_vector> 
	 	 	 <radius_vector> 
	 	 	 	 <x_start>2742</x_start> 
	 	 	 	 <y_start>3053</y_start> 
	 	 	 	 <x_end>2697</x_end> 
	 	 	 	 <y_end>3020</y_end> 
	 	 	 </radius_vectors> 
	 	 </vectors> 
	 <object> 
	 	 <name>branch_12</name> 
	 	 <pose>Unspecified</pose> 
	 	 <truncated>0</truncated> 
	 	 <difficult>0</difficult> 
	 	 <bndbox> 
	 	 	 <xmin>2586</xmin> 
	 	 	 <ymin> 2971</ymin> 
	 	 	 <xmax>2730</xmax> 
	 	 	 <ymax>3183</ymax> 
	 	 </bndbox> 
	 <object> 
	 	 <vectors> 
	 	 	 <direction_vector> 
	 	 	 	 <x_start>2643</x_start> 
	 	 	 	 <y_start>3078</y_start> 
	 	 	 	 <x_end>2677</x_end> 
	 	 	 	 <y_end>3072</y_end> 
	 	 	 </direction_vector> 
	 	 	 <radius_vector> 
	 	 	 	 <x_start>2643</x_start> 
	 	 	 	 <y_start>3078</y_start> 
	 	 	 	 <x_end>2631</x_end> 
	 	 	 	 <y_end>2999</y_end> 
	 	 	 </radius_vectors> 
	 	 </vectors> 
	 <object> 
	 	 <name>branch_13</name> 
	 	 <pose>Unspecified</pose> 
	 	 <truncated>0</truncated> 
	 	 <difficult>0</difficult> 
	 	 <bndbox> 
	 	 	 <xmin>2151</xmin> 
	 	 	 <ymin> 2172</ymin> 
	 	 	 <xmax>2909</xmax> 
	 	 	 <ymax>3648</ymax> 
	 	 </bndbox> 
	 <object> 
	 	 <vectors> 
	 	 	 <direction_vector> 
	 	 	 	 <x_start>2638</x_start> 
	 	 	 	 <y_start>2970</y_start> 
	 	 	 	 <x_end>2706</x_end> 
	 	 	 	 <y_end>2808</y_end> 
	 	 	 </direction_vector> 
	 	 	 <radius_vector> 
	 	 	 	 <x_start>2638</x_start> 
	 	 	 	 <y_start>2970</y_start> 
	 	 	 	 <x_end>2560</x_end> 
	 	 	 	 <y_end>2942</y_end> 
	 	 	 </radius_vectors> 
	 	 </vectors> 
	 <object> 
	 	 <name>branch_14</name> 
	 	 <pose>Unspecified</pose> 
	 	 <truncated>0</truncated> 
	 	 <difficult>0</difficult> 
	 	 <bndbox> 
	 	 	 <xmin>2606</xmin> 
	 	 	 <ymin> 1158</ymin> 
	 	 	 <xmax>2918</xmax> 
	 	 	 <ymax>2175</ymax> 
	 	 </bndbox> 
	 <object> 
	 	 <vectors> 
	 	 	 <direction_vector> 
	 	 	 	 <x_start>2765</x_start> 
	 	 	 	 <y_start>1673</y_start> 
	 	 	 	 <x_end>2734</x_end> 
	 	 	 	 <y_end>1492</y_end> 
	 	 	 </direction_vector> 
	 	 	 <radius_vector> 
	 	 	 	 <x_start>2765</x_start> 
	 	 	 	 <y_start>1673</y_start> 
	 	 	 	 <x_end>2691</x_end> 
	 	 	 	 <y_end>1698</y_end> 
	 	 	 </radius_vectors> 
	 	 </vectors> 
	 <object> 
	 	 <name>branch_15</name> 
	 	 <pose>Unspecified</pose> 
	 	 <truncated>0</truncated> 
	 	 <difficult>0</difficult> 
	 	 <bndbox> 
	 	 	 <xmin>2913</xmin> 
	 	 	 <ymin> 2149</ymin> 
	 	 	 <xmax>3106</xmax> 
	 	 	 <ymax>2390</ymax> 
	 	 </bndbox> 
	 <object> 
	 	 <vectors> 
	 	 	 <direction_vector> 
	 	 	 	 <x_start>2999</x_start> 
	 	 	 	 <y_start>2263</y_start> 
	 	 	 	 <x_end>3039</x_end> 
	 	 	 	 <y_end>2204</y_end> 
	 	 	 </direction_vector> 
	 	 	 <radius_vector> 
	 	 	 	 <x_start>2999</x_start> 
	 	 	 	 <y_start>2263</y_start> 
	 	 	 	 <x_end>2981</x_end> 
	 	 	 	 <y_end>2247</y_end> 
	 	 	 </radius_vectors> 
	 	 </vectors> 
	 <object> 
	 	 <name>branch_16</name> 
	 	 <pose>Unspecified</pose> 
	 	 <truncated>0</truncated> 
	 	 <difficult>0</difficult> 
	 	 <bndbox> 
	 	 	 <xmin>3050</xmin> 
	 	 	 <ymin> 1980</ymin> 
	 	 	 <xmax>3192</xmax> 
	 	 	 <ymax>2154</ymax> 
	 	 </bndbox> 
	 <object> 
	 	 <vectors> 
	 	 	 <direction_vector> 
	 	 	 	 <x_start>3130</x_start> 
	 	 	 	 <y_start>2065</y_start> 
	 	 	 	 <x_end>3152</x_end> 
	 	 	 	 <y_end>2013</y_end> 
	 	 	 </direction_vector> 
	 	 	 <radius_vector> 
	 	 	 	 <x_start>3130</x_start> 
	 	 	 	 <y_start>2065</y_start> 
	 	 	 	 <x_end>3107</x_end> 
	 	 	 	 <y_end>2056</y_end> 
	 	 	 </radius_vectors> 
	 	 </vectors> 
	 <object> 
	 	 <name>branch_17</name> 
	 	 <pose>Unspecified</pose> 
	 	 <truncated>0</truncated> 
	 	 <difficult>0</difficult> 
	 	 <bndbox> 
	 	 	 <xmin>1213</xmin> 
	 	 	 <ymin> 3062</ymin> 
	 	 	 <xmax>1471</xmax> 
	 	 	 <ymax>3241</ymax> 
	 	 </bndbox> 
	 <object> 
	 	 <vectors> 
	 	 	 <direction_vector> 
	 	 	 	 <x_start>1339</x_start> 
	 	 	 	 <y_start>3140</y_start> 
	 	 	 	 <x_end>1390</x_end> 
	 	 	 	 <y_end>3103</y_end> 
	 	 	 </direction_vector> 
	 	 	 <radius_vector> 
	 	 	 	 <x_start>1339</x_start> 
	 	 	 	 <y_start>3140</y_start> 
	 	 	 	 <x_end>1310</x_end> 
	 	 	 	 <y_end>3099</y_end> 
	 	 	 </radius_vectors> 
	 	 </vectors> 
	 <object> 
	 	 <name>branch_18</name> 
	 	 <pose>Unspecified</pose> 
	 	 <truncated>0</truncated> 
	 	 <difficult>0</difficult> 
	 	 <bndbox> 
	 	 	 <xmin>1364</xmin> 
	 	 	 <ymin> 3025</ymin> 
	 	 	 <xmax>1483</xmax> 
	 	 	 <ymax>3128</ymax> 
	 	 </bndbox> 
	 <object> 
	 	 <vectors> 
	 	 	 <direction_vector> 
	 	 	 	 <x_start>1422</x_start> 
	 	 	 	 <y_start>3072</y_start> 
	 	 	 	 <x_end>1419</x_end> 
	 	 	 	 <y_end>3042</y_end> 
	 	 	 </direction_vector> 
	 	 	 <radius_vector> 
	 	 	 	 <x_start>1422</x_start> 
	 	 	 	 <y_start>3072</y_start> 
	 	 	 	 <x_end>1369</x_end> 
	 	 	 	 <y_end>3072</y_end> 
	 	 	 </radius_vectors> 
	 	 </vectors> 
	 <object> 
	 	 <name>branch_19</name> 
	 	 <pose>Unspecified</pose> 
	 	 <truncated>0</truncated> 
	 	 <difficult>0</difficult> 
	 	 <bndbox> 
	 	 	 <xmin>1331</xmin> 
	 	 	 <ymin> 2878</ymin> 
	 	 	 <xmax>1473</xmax> 
	 	 	 <ymax>3022</ymax> 
	 	 </bndbox> 
	 <object> 
	 	 <vectors> 
	 	 	 <direction_vector> 
	 	 	 	 <x_start>1391</x_start> 
	 	 	 	 <y_start>2948</y_start> 
	 	 	 	 <x_end>1367</x_end> 
	 	 	 	 <y_end>2914</y_end> 
	 	 	 </direction_vector> 
	 	 	 <radius_vector> 
	 	 	 	 <x_start>1391</x_start> 
	 	 	 	 <y_start>2948</y_start> 
	 	 	 	 <x_end>1340</x_end> 
	 	 	 	 <y_end>2975</y_end> 
	 	 	 </radius_vectors> 
	 	 </vectors> 
	 <object> 
	 	 <name>branch_20</name> 
	 	 <pose>Unspecified</pose> 
	 	 <truncated>0</truncated> 
	 	 <difficult>0</difficult> 
	 	 <bndbox> 
	 	 	 <xmin>957</xmin> 
	 	 	 <ymin> 2397</ymin> 
	 	 	 <xmax>1238</xmax> 
	 	 	 <ymax>2718</ymax> 
	 	 </bndbox> 
	 <object> 
	 	 <vectors> 
	 	 	 <direction_vector> 
	 	 	 	 <x_start>1071</x_start> 
	 	 	 	 <y_start>2538</y_start> 
	 	 	 	 <x_end>1021</x_end> 
	 	 	 	 <y_end>2472</y_end> 
	 	 	 </direction_vector> 
	 	 	 <radius_vector> 
	 	 	 	 <x_start>1071</x_start> 
	 	 	 	 <y_start>2538</y_start> 
	 	 	 	 <x_end>1028</x_end> 
	 	 	 	 <y_end>2566</y_end> 
	 	 	 </radius_vectors> 
	 	 </vectors> 
	 <object> 
	 	 <name>branch_21</name> 
	 	 <pose>Unspecified</pose> 
	 	 <truncated>0</truncated> 
	 	 <difficult>0</difficult> 
	 	 <bndbox> 
	 	 	 <xmin>1129</xmin> 
	 	 	 <ymin> 2686</ymin> 
	 	 	 <xmax>1436</xmax> 
	 	 	 <ymax>2948</ymax> 
	 	 </bndbox> 
	 <object> 
	 	 <vectors> 
	 	 	 <direction_vector> 
	 	 	 	 <x_start>1267</x_start> 
	 	 	 	 <y_start>2805</y_start> 
	 	 	 	 <x_end>1195</x_end> 
	 	 	 	 <y_end>2735</y_end> 
	 	 	 </direction_vector> 
	 	 	 <radius_vector> 
	 	 	 	 <x_start>1267</x_start> 
	 	 	 	 <y_start>2805</y_start> 
	 	 	 	 <x_end>1235</x_end> 
	 	 	 	 <y_end>2833</y_end> 
	 	 	 </radius_vectors> 
	 	 </vectors> 
	 <object> 
	 	 <name>branch_22</name> 
	 	 <pose>Unspecified</pose> 
	 	 <truncated>0</truncated> 
	 	 <difficult>0</difficult> 
	 	 <bndbox> 
	 	 	 <xmin>761</xmin> 
	 	 	 <ymin> 2203</ymin> 
	 	 	 <xmax>1019</xmax> 
	 	 	 <ymax>2404</ymax> 
	 	 </bndbox> 
	 <object> 
	 	 <vectors> 
	 	 	 <direction_vector> 
	 	 	 	 <x_start>881</x_start> 
	 	 	 	 <y_start>2299</y_start> 
	 	 	 	 <x_end>827</x_end> 
	 	 	 	 <y_end>2246</y_end> 
	 	 	 </direction_vector> 
	 	 	 <radius_vector> 
	 	 	 	 <x_start>881</x_start> 
	 	 	 	 <y_start>2299</y_start> 
	 	 	 	 <x_end>842</x_end> 
	 	 	 	 <y_end>2323</y_end> 
	 	 	 </radius_vectors> 
	 	 </vectors> 
	 <object> 
	 	 <name>branch_23</name> 
	 	 <pose>Unspecified</pose> 
	 	 <truncated>0</truncated> 
	 	 <difficult>0</difficult> 
	 	 <bndbox> 
	 	 	 <xmin>1071</xmin> 
	 	 	 <ymin> 3021</ymin> 
	 	 	 <xmax>1561</xmax> 
	 	 	 <ymax>3648</ymax> 
	 	 </bndbox> 
	 <object> 
	 	 <vectors> 
	 	 	 <direction_vector> 
	 	 	 	 <x_start>1295</x_start> 
	 	 	 	 <y_start>3340</y_start> 
	 	 	 	 <x_end>1249</x_end> 
	 	 	 	 <y_end>3245</y_end> 
	 	 	 </direction_vector> 
	 	 	 <radius_vector> 
	 	 	 	 <x_start>1295</x_start> 
	 	 	 	 <y_start>3340</y_start> 
	 	 	 	 <x_end>1232</x_end> 
	 	 	 	 <y_end>3368</y_end> 
	 	 	 </radius_vectors> 
	 	 </vectors> 
	 <object> 
	 	 <name>branch_24</name> 
	 	 <pose>Unspecified</pose> 
	 	 <truncated>0</truncated> 
	 	 <difficult>0</difficult> 
	 	 <bndbox> 
	 	 	 <xmin>1408</xmin> 
	 	 	 <ymin> 124</ymin> 
	 	 	 <xmax>1601</xmax> 
	 	 	 <ymax>611</ymax> 
	 	 </bndbox> 
	 <object> 
	 	 <vectors> 
	 	 	 <direction_vector> 
	 	 	 	 <x_start>1497</x_start> 
	 	 	 	 <y_start>368</y_start> 
	 	 	 	 <x_end>1467</x_end> 
	 	 	 	 <y_end>235</y_end> 
	 	 	 </direction_vector> 
	 	 	 <radius_vector> 
	 	 	 	 <x_start>1497</x_start> 
	 	 	 	 <y_start>368</y_start> 
	 	 	 	 <x_end>1479</x_end> 
	 	 	 	 <y_end>373</y_end> 
	 	 	 </radius_vectors> 
	 	 </vectors> 
	 <object> 
	 	 <name>branch_25</name> 
	 	 <pose>Unspecified</pose> 
	 	 <truncated>0</truncated> 
	 	 <difficult>0</difficult> 
	 	 <bndbox> 
	 	 	 <xmin>1489</xmin> 
	 	 	 <ymin> 599</ymin> 
	 	 	 <xmax>1645</xmax> 
	 	 	 <ymax>1185</ymax> 
	 	 </bndbox> 
	 <object> 
	 	 <vectors> 
	 	 	 <direction_vector> 
	 	 	 	 <x_start>1576</x_start> 
	 	 	 	 <y_start>863</y_start> 
	 	 	 	 <x_end>1549</x_end> 
	 	 	 	 <y_end>689</y_end> 
	 	 	 </direction_vector> 
	 	 	 <radius_vector> 
	 	 	 	 <x_start>1576</x_start> 
	 	 	 	 <y_start>863</y_start> 
	 	 	 	 <x_end>1547</x_end> 
	 	 	 	 <y_end>870</y_end> 
	 	 	 </radius_vectors> 
	 	 </vectors> 
	 <object> 
	 	 <name>branch_26</name> 
	 	 <pose>Unspecified</pose> 
	 	 <truncated>0</truncated> 
	 	 <difficult>0</difficult> 
	 	 <bndbox> 
	 	 	 <xmin>2444</xmin> 
	 	 	 <ymin> 775</ymin> 
	 	 	 <xmax>2759</xmax> 
	 	 	 <ymax>1586</ymax> 
	 	 </bndbox> 
	 <object> 
	 	 <vectors> 
	 	 	 <direction_vector> 
	 	 	 	 <x_start>2609</x_start> 
	 	 	 	 <y_start>1118</y_start> 
	 	 	 	 <x_end>2562</x_end> 
	 	 	 	 <y_end>967</y_end> 
	 	 	 </direction_vector> 
	 	 	 <radius_vector> 
	 	 	 	 <x_start>2609</x_start> 
	 	 	 	 <y_start>1118</y_start> 
	 	 	 	 <x_end>2557</x_end> 
	 	 	 	 <y_end>1132</y_end> 
	 	 	 </radius_vectors> 
	 	 </vectors> 
	 <object> 
	 	 <name>branch_27</name> 
	 	 <pose>Unspecified</pose> 
	 	 <truncated>0</truncated> 
	 	 <difficult>0</difficult> 
	 	 <bndbox> 
	 	 	 <xmin>2396</xmin> 
	 	 	 <ymin> 468</ymin> 
	 	 	 <xmax>2578</xmax> 
	 	 	 <ymax>766</ymax> 
	 	 </bndbox> 
	 <object> 
	 	 <vectors> 
	 	 	 <direction_vector> 
	 	 	 	 <x_start>2470</x_start> 
	 	 	 	 <y_start>603</y_start> 
	 	 	 	 <x_end>2455</x_end> 
	 	 	 	 <y_end>494</y_end> 
	 	 	 </direction_vector> 
	 	 	 <radius_vector> 
	 	 	 	 <x_start>2470</x_start> 
	 	 	 	 <y_start>603</y_start> 
	 	 	 	 <x_end>2401</x_end> 
	 	 	 	 <y_end>610</y_end> 
	 	 	 </radius_vectors> 
	 	 </vectors> 
	 <object> 
	 	 <name>branch_28</name> 
	 	 <pose>Unspecified</pose> 
	 	 <truncated>0</truncated> 
	 	 <difficult>0</difficult> 
	 	 <bndbox> 
	 	 	 <xmin>2207</xmin> 
	 	 	 <ymin> 1</ymin> 
	 	 	 <xmax>2505</xmax> 
	 	 	 <ymax>463</ymax> 
	 	 </bndbox> 
	 <object> 
	 	 <vectors> 
	 	 	 <direction_vector> 
	 	 	 	 <x_start>2384</x_start> 
	 	 	 	 <y_start>245</y_start> 
	 	 	 	 <x_end>2337</x_end> 
	 	 	 	 <y_end>151</y_end> 
	 	 	 </direction_vector> 
	 	 	 <radius_vector> 
	 	 	 	 <x_start>2384</x_start> 
	 	 	 	 <y_start>245</y_start> 
	 	 	 	 <x_end>2337</x_end> 
	 	 	 	 <y_end>271</y_end> 
	 	 	 </radius_vectors> 
	 	 </vectors> 
</annotation>
